codesafe/__init__.py
codesafe-0.0.3.dist-info/licenses/LICENSE
codesafe-0.0.3.dist-info/METADATA
codesafe-0.0.3.dist-info/WHEEL
codesafe-0.0.3.dist-info/top_level.txt
codesafe-0.0.3.dist-info/RECORD
